{"trace_id": "trace_ed4b8b6a", "timestamp": "2026-04-30T07:35:06.000439+00:00", "type": "ACTION", "data": {"trace_id": "trace_ed4b8b6a", "action_type": "monitor", "target_role": "authority", "timestamp": "2026-04-30T07:35:06.000439+00:00", "context": {"source": "dashboard", "row": 3}, "signal_id": "S_2"}}
{"trace_id": "trace_5c2c9f44", "timestamp": "2026-04-30T07:35:16.255244+00:00", "type": "ACTION", "data": {"trace_id": "trace_5c2c9f44", "action_type": "eligible_for_escalation", "target_role": "authority", "timestamp": "2026-04-30T07:35:16.255244+00:00", "context": {"source": "dashboard", "row": 7}, "signal_id": "S_6"}}
{"trace_id": "trace_d2274595", "timestamp": "2026-04-30T07:45:27.225464+00:00", "type": "ACTION", "data": {"trace_id": "trace_d2274595", "action_type": "eligible_for_escalation", "target_role": "authority", "timestamp": "2026-04-30T07:45:27.225464+00:00", "context": {"source": "dashboard", "row": 7}, "signal_id": "S_6"}}
{"trace_id": "trace_684b8e25", "timestamp": "2026-04-30T07:45:50.633122+00:00", "type": "ACTION", "data": {"trace_id": "trace_684b8e25", "action_type": "eligible_for_escalation", "target_role": "authority", "timestamp": "2026-04-30T07:45:50.633122+00:00", "context": {"source": "dashboard", "row": 7}, "signal_id": "S_6"}}
{"trace_id": "trace_2266e2bb", "timestamp": "2026-04-30T09:18:12.554337+00:00", "type": "ACTION", "data": {"trace_id": "trace_2266e2bb", "action_type": "requires_review", "target_role": "authority", "timestamp": "2026-04-30T09:18:12.554337+00:00", "context": {"source": "dashboard", "row": 1}, "signal_id": "S_0"}}
{"trace_id": "trace_104dcf71", "timestamp": "2026-04-30T09:18:14.756541+00:00", "type": "ACTION", "data": {"trace_id": "trace_104dcf71", "action_type": "monitor", "target_role": "authority", "timestamp": "2026-04-30T09:18:14.756541+00:00", "context": {"source": "dashboard", "row": 2}, "signal_id": "S_1"}}
{"trace_id": "trace_98436e0f", "timestamp": "2026-04-30T09:18:27.188110+00:00", "type": "ACTION", "data": {"trace_id": "trace_98436e0f", "action_type": "monitor", "target_role": "authority", "timestamp": "2026-04-30T09:18:27.188110+00:00", "context": {"source": "dashboard", "row": 2}, "signal_id": "S_1"}}
{"trace_id": "trace_aefdbf62", "timestamp": "2026-04-30T09:18:28.211907+00:00", "type": "ACTION", "data": {"trace_id": "trace_aefdbf62", "action_type": "eligible_for_escalation", "target_role": "authority", "timestamp": "2026-04-30T09:18:28.211907+00:00", "context": {"source": "dashboard", "row": 3}, "signal_id": "S_2"}}
{"trace_id": "trace_047fb74b", "timestamp": "2026-04-30T09:18:29.331858+00:00", "type": "ACTION", "data": {"trace_id": "trace_047fb74b", "action_type": "requires_review", "target_role": "authority", "timestamp": "2026-04-30T09:18:29.331858+00:00", "context": {"source": "dashboard", "row": 4}, "signal_id": "S_3"}}
{"trace_id": "trace_2192a697", "timestamp": "2026-04-30T09:22:26.257515+00:00", "type": "ACTION", "data": {"trace_id": "trace_2192a697", "action_type": "eligible_for_escalation", "target_role": "authority", "timestamp": "2026-04-30T09:22:26.257515+00:00", "context": {"source": "dashboard", "row": 3}, "signal_id": "S_2"}}
